{
	"module": "rally",
	"name": "Rally",
	"title": "Scheduler",
	"category": "Productivity",
	"version": "v4.5.1",
	"installMethod": "clone",
	"web": true,
	"essential": false,
	"finished": false,
	"ai": false,
	"database": "",
	"github": "lukevella/rallly",
	"description": "A scheduling and collaboration tool designed to make organizing events and meetings easier.",
	"keywords": [
		"Availability checker",
		"Collaboration software",
		"Event planner",
		"Group meetings",
		"Meeting organizer",
		"Meeting polls",
		"Scheduler",
		"Scheduling tool",
		"Team coordination"
	],
	"proprietary": [],
	"default": {
		"enabled": true,
		"localPort": 9507,
		"permissions": [
			"user"
		]
	}
}
